setup.py
django_cookies.egg-info/PKG-INFO
django_cookies.egg-info/SOURCES.txt
django_cookies.egg-info/dependency_links.txt
django_cookies.egg-info/top_level.txt
djcookies/__init__.py
djcookies/middleware.py