Metadata-Version: 1.0
Name: django-cookies
Version: 0.0.2
Summary: Drop-in replacement for Django's request.COOKIES
Home-page: http://github.com/dcramer/django-cookies
Author: David Cramer
Author-email: dcramer@gmail.com
License: UNKNOWN
Platform: UNKNOWN
Classifier: Framework :: Django
Classifier: Intended Audience :: Developers
Classifier: Intended Audience :: System Administrators
Classifier: Operating System :: OS Independent
Classifier: Topic :: Software Development
